gor_pyspark/__init__.py
gor_pyspark/gorspark.py
gor_pyspark-3.19.0.dist-info/LICENSE
gor_pyspark-3.19.0.dist-info/METADATA
gor_pyspark-3.19.0.dist-info/WHEEL
gor_pyspark-3.19.0.dist-info/top_level.txt
gor_pyspark-3.19.0.dist-info/RECORD
