Metadata-Version: 2.1
Name: gor-pyspark
Version: 3.19.0
Summary: Python helper function for gor-spark
Home-page: https://github.com/gorpipe/gor-pyspark
Author: Sigmar Stefansson
Author-email: sigmar@genuitysci.com
License: UNKNOWN
Project-URL: Bug Tracker, https://github.com/gorpipe/gor-pyspark/issues
Platform: UNKNOWN
Classifier: Programming Language :: Python :: 3
Classifier: License :: OSI Approved :: Apache Software License
Classifier: Operating System :: OS Independent
Requires-Python: >=3.6
License-File: LICENSE
